{
  "name": "Testando",
  "about_url": "https://github.com/eduHanjos0411/RemoteThemeDiscourse/blob/main/about.json ",
  "license_url": "https://github.com/eduHanjos0411/RemoteThemeDiscourse/blob/main/LICENSE ",
  "assets": {
        "asset-variable": "assets/background.svg"
  },
  "color_schemes": {
    "CoresTestando": {
          "primary": "6d00a8",
          "secondary": "000000",
          "tertiary": "c532fb",
          "quaternary": "ffffff",
          "header_background": "fff700",
          "header_primary": "9e02f2",
          "highlight": "fafa00",
          "danger": "c80001",
          "success": "009900",
          "love": "ff1a4f",
          "selected": "26b5fd",
          "hover": "ffffff"
        }
    }
}
